qa_pytest_rabbitmq-0.0.13.dist-info/METADATA
qa_pytest_rabbitmq-0.0.13.dist-info/WHEEL
qa_pytest_rabbitmq-0.0.13.dist-info/entry_points.txt
qa_pytest_rabbitmq/__init__.py
qa_pytest_rabbitmq/_abstract_queue_handler_tests.py
qa_pytest_rabbitmq/_version.py
qa_pytest_rabbitmq/logging.ini
qa_pytest_rabbitmq/queue_handler.py
qa_pytest_rabbitmq/rabbitmq_configuration.py
qa_pytest_rabbitmq/rabbitmq_steps.py
qa_pytest_rabbitmq/rabbitmq_tests.py
qa_pytest_rabbitmq-0.0.13.dist-info/RECORD
